lamport_256.py
lamport_256-0.1.dist-info/LICENSE
lamport_256-0.1.dist-info/METADATA
lamport_256-0.1.dist-info/WHEEL
lamport_256-0.1.dist-info/top_level.txt
lamport_256-0.1.dist-info/RECORD
