Metadata-Version: 2.1
Name: lamport-256
Version: 0.1
Summary: Simple single use Lamport signature scheme
Home-page: https://github.com/johnpaulkiser/lamport-256
Author: JP Kiser
Author-email: johnpaulkiser@gmail.com
License: UNKNOWN
Platform: UNKNOWN
Classifier: Programming Language :: Python :: 3
Classifier: License :: OSI Approved :: MIT License
Classifier: Operating System :: OS Independent
Requires-Python: >3.6
